Project/__init__.py
Project/main.py
Project/ngrok.exe
Project/script.py
Project/server.py
Project/style.py
Project/style_fw.py
Project/Picture/Actions.png
Project/Picture/Actions1.png
Project/Picture/Actions2.png
Project/Picture/Actions3.png
Project/Picture/Actions4.png
Project/Picture/Actions5.png
Project/Picture/Actions6.png
Project/Picture/Actions7.png
Project/Picture/Actions8.png
Project/Picture/Actions9.png
Project/Picture/Close-List.png
Project/Picture/Create.png
Project/Picture/Figure.png
Project/Picture/File.png
Project/Picture/Home.png
Project/Picture/List.png
Project/Picture/Logo.png
Project/Picture/MainLogo.png
Project/Picture/NameLogo.png
Project/Picture/Oval.png
Project/Picture/Pero.png
Project/Picture/Picture.png
Project/Picture/Rect.png
Project/Picture/Size.png
Project/Picture/back.png
Project/Picture/back2.png
Project/Picture/close.png
Project/Picture/play.png
Project/Picture/save.png
Project/Picture/svernut.png
Project/Sound/aaaaflp.mp3
Project/Sound/click_sound.mp3
Project/cash/key.txt
Project/data/__init__.py
Project/data/backend.py
Project/data/css.py
Project/data/mouse.py
Project/data/scriptToSaveProject.py
Project/templates/base.html
Benefer-1.0.0.dist-info/METADATA
Benefer-1.0.0.dist-info/WHEEL
Benefer-1.0.0.dist-info/entry_points.txt
Benefer-1.0.0.dist-info/top_level.txt
Benefer-1.0.0.dist-info/RECORD
